[
    {
        "type": "hudson-build-status",
        "dataUri": "/widget/hudson-build-status/test",
        "size": { "width": 1, "height": 1 },
        "options": {
            "title": "Jenkins POM",
            "project": "http://ci.jenkins-ci.org/job/jenkins_pom"
        },
        "position": { "row": 1, "col": 1 }
    },
    {
        "type": "hudson-build-status",
        "dataUri": "/widget/hudson-build-status/test",
        "size": { "width": 1, "height": 1 },
        "options": {
            "title": "Jenkins trunk",
            "project": "http://ci.jenkins-ci.org/job/jenkins_main_trunk"
        },
        "position": { "row": 1, "col": 2 }
    },
    {
        "type": "teamcity-build-status",
        "dataUri": "/widget/teamcity-build-status/test",
        "size": { "width": 1, "height": 1 },
        "options": {
            "title": "IntelliJ IDEA",
            "buildType": "http://teamcity.jetbrains.com/guestAuth/app/rest/builds/buildType:bt343"
        },
        "position": { "row": 1, "col": 3 }
    },
    {
        "type": "ping",
        "dataUri": "/widget/ping/test",
        "size": { "width": 1, "height": 1 },
        "options": { "title": "Google" },
        "position": { "row": 1, "col": 4 }
    },
    {
        "type": "countdown",
        "dataUri": "/widget/countdown/test",
        "size": { "width": 1, "height": 1 },
        "options": { "title": "in iteration" },
        "position": { "row": 2, "col": 1 }
    },
    {
        "type": "jira-burn-up",
        "dataUri": "/widget/jira-burn-up/test",
        "size": { "width": 3, "height": 1 },
        "position": { "row": 2, "col": 2 }
    },
    {
        "type": "sonar-code-coverage",
        "dataUri": "/widget/sonar-code-coverage/test",
        "size": { "width": 2, "height": 1 },
        "options": {
            "title": "Spring integration",
            "project": "https://sonar.springsource.org/api/resources?resource=org.springframework.integration:spring-integration&metrics=coverage"
        },
        "position": { "row": 3, "col": 1 }
    }
]
